shlexwhichplus/README.md
shlexwhichplus/__init__.py
shlexwhichplus/requirements.txt
shlexwhichplus/thirdparty.json
shlexwhichplus-0.10.dist-info/LICENSE.rst
shlexwhichplus-0.10.dist-info/METADATA
shlexwhichplus-0.10.dist-info/WHEEL
shlexwhichplus-0.10.dist-info/top_level.txt
shlexwhichplus-0.10.dist-info/RECORD
