Metadata-Version: 2.1
Name: shlexwhichplus
Version: 0.10
Summary: Like shutil.which, but for all file types, and multiple results (if desired)
Home-page: https://github.com/hansalemaos/shlexwhichplus
Author: Johannes Fischer
Author-email: aulasparticularesdealemaosp@gmail.com
License: MIT
Keywords: shutil,which,search
Classifier: Development Status :: 4 - Beta
Classifier: Programming Language :: Python :: 3 :: Only
Classifier: Programming Language :: Python :: 3.10
Classifier: Topic :: Software Development :: Libraries :: Python Modules
Classifier: Topic :: Utilities
License-File: LICENSE.rst
